diagrams_patterns/__init__.py
diagrams_patterns/aws.py
diagrams_patterns/neato.py
diagrams_patterns/neato_aws.py
diagrams_patterns-0.1.0a1.dist-info/LICENSE
diagrams_patterns-0.1.0a1.dist-info/METADATA
diagrams_patterns-0.1.0a1.dist-info/WHEEL
diagrams_patterns-0.1.0a1.dist-info/RECORD
