Metadata-Version: 2.1
Name: diagrams_patterns
Version: 0.1.0a1
Summary: a collection of patterns for diagrams that can be reused in different projects
License: MIT
Author: Anddd7
Author-email: anddd7@icloud.com
Requires-Python: >=3.12,<4.0
Classifier: License :: OSI Approved :: MIT License
Classifier: Programming Language :: Python :: 3
Classifier: Programming Language :: Python :: 3.12
Requires-Dist: diagrams-ext (>=0.23.5a4,<0.24.0)
